solarmap/__init__.py
solarmap/sclocation.py
solarmap-0.0.16.dist-info/LICENSE
solarmap-0.0.16.dist-info/METADATA
solarmap-0.0.16.dist-info/WHEEL
solarmap-0.0.16.dist-info/top_level.txt
solarmap-0.0.16.dist-info/RECORD
