Metadata-Version: 2.1
Name: solarmap
Version: 0.0.16
Summary: Get HEE Coordinates for spacecraft around the Sun
Author: Luis Alberto Canizares
Author-email: <canizares@cp.dias.ie>
Keywords: python,solar,nasa,esa,spacecraft,coordinates,sun,corona,parker,solar orbiter,bepicolombo
Classifier: Development Status :: 3 - Alpha
Classifier: Intended Audience :: Developers
Classifier: Programming Language :: Python :: 3
Classifier: Operating System :: Unix
Classifier: Operating System :: MacOS :: MacOS X
Classifier: Operating System :: Microsoft :: Windows
License-File: LICENSE
Requires-Dist: sunpy
Requires-Dist: astropy
Requires-Dist: astroquery
